Metadata-Version: 1.1
Name: Flask-Locale
Version: 1.0.2
Summary: Adds i18n/l10n support to Flask applications easily. Uses CSV files(or database) to load translations.
Home-page: http://github.com/derkan/flask-locale
Author: Erkan Durmus
Author-email: derkan@gmail.com
License: BSD
Platform: any
Classifier: Environment :: Web Environment
Classifier: Intended Audience :: Developers
Classifier: License :: OSI Approved :: BSD License
Classifier: Operating System :: OS Independent
Classifier: Programming Language :: Python
Classifier: Programming Language :: Python :: 3
Classifier: Topic :: Internet :: WWW/HTTP :: Dynamic Content
Classifier: Topic :: Software Development :: Libraries :: Python Modules
